.gitignore
paper.txt
setup.py
magnet/__init__.py
magnet/cpu_model.py
magnet/cutils.c
magnet/cutils.pyx
magnet/layers.py
magnet/losses.py
magnet/model.py
magnet/transformation.py
magnet_learn.egg-info/PKG-INFO
magnet_learn.egg-info/SOURCES.txt
magnet_learn.egg-info/dependency_links.txt
magnet_learn.egg-info/requires.txt
magnet_learn.egg-info/top_level.txt
tests/cycle.py
tests/mnist.py
tests/n2v.py
tests/simple_examples.py