Metadata-Version: 1.1
Name: magnet-learn
Version: 0.0.2
Summary: MAnifold learning form weighted Graphs and NETworks
Home-page: https://github.com/kerighan/magnet
Author: Maixent Chenebaux
Author-email: max.chbx@gmail.com
License: UNKNOWN
Platform: UNKNOWN
Classifier: Programming Language :: Python :: 3
Classifier: Programming Language :: Python :: 3.7
Classifier: License :: OSI Approved :: MIT License
Classifier: Operating System :: OS Independent
